LICENSE
MANIFEST.in
README.rst
requirements.txt
setup.py
malcarve/__init__.py
malcarve/config.py
malcarve/scan.py
malcarve/version.py
malcarve/web.py
malcarve.egg-info/PKG-INFO
malcarve.egg-info/SOURCES.txt
malcarve.egg-info/dependency_links.txt
malcarve.egg-info/entry_points.txt
malcarve.egg-info/not-zip-safe
malcarve.egg-info/requires.txt
malcarve.egg-info/top_level.txt
malcarve/conf/malcarve.conf
malcarve/ext/Makefile
malcarve/ext/include/xorpatterns.h
malcarve/ext/lib/linux/x86_32/.empty
malcarve/ext/lib/linux/x86_32/xorpatterns.so
malcarve/ext/lib/linux/x86_64/.empty
malcarve/ext/lib/linux/x86_64/xorpatterns.so
malcarve/ext/lib/windows/x86_32/.empty
malcarve/ext/lib/windows/x86_32/xorpatterns.dll
malcarve/ext/lib/windows/x86_64/.empty
malcarve/ext/lib/windows/x86_64/xorpatterns.dll
malcarve/ext/src/xorpatterns.c
malcarve/html/api.html
malcarve/html/base.html
malcarve/html/results.html
malcarve/html/submit.html
malcarve/html/css/bootstrap-responsive.min.css
malcarve/html/css/bootstrap.min.css
malcarve/html/img/glyphicons-halflings-white.png
malcarve/html/img/glyphicons-halflings.png
malcarve/html/js/bootstrap-filestyle.min.js
malcarve/html/js/bootstrap.min.js
malcarve/html/js/jquery.js
malcarve/payloads/__init__.py
malcarve/payloads/flash.py
malcarve/payloads/ole2.py
malcarve/payloads/pdf.py
malcarve/payloads/pe.py
malcarve/payloads/strings.py
malcarve/payloads/zip.py
malcarve/schemes/__init__.py
malcarve/schemes/add.py
malcarve/schemes/rol.py
malcarve/schemes/xor.py
malcarve/streams/__init__.py
malcarve/streams/ascii.py
malcarve/streams/deflate.py
malcarve/streams/reverse.py