Metadata-Version: 2.1
Name: malcarve
Version: 0.5
Summary: Obfuscated payload extractor for malware samples
Home-page: https://github.com/shendo/malcarve
Author: Steve Henderson
Author-email: steve.henderson@hendotech.com.au
License: GPL
Platform: UNKNOWN
Classifier: Development Status :: 4 - Beta
Classifier: Intended Audience :: Developers
Classifier: Intended Audience :: System Administrators
Classifier: License :: OSI Approved :: GNU General Public License v3 or later (GPLv3+)
Classifier: Operating System :: OS Independent
Classifier: Programming Language :: Python
Classifier: Programming Language :: Python :: 3
Classifier: Programming Language :: Python :: 3.7
Classifier: Topic :: Internet
Classifier: Topic :: Security
License-File: LICENSE
